nicexcel/__init__.py
nicexcel/const.py
nicexcel/excel_format.py
nicexcel/utils.py
nicexcel/wrapper.py
test/__init__.py
test/test_wrapper.py
nicexcel-0.1.12.dist-info/LICENCE
nicexcel-0.1.12.dist-info/METADATA
nicexcel-0.1.12.dist-info/WHEEL
nicexcel-0.1.12.dist-info/top_level.txt
nicexcel-0.1.12.dist-info/RECORD
