Metadata-Version: 2.1
Name: nicexcel
Version: 0.1.12
Summary: A package for writing nicely formatted Pandas dataframes in Excel data files
Home-page: https://github.com/scouseralex/nicexcel
License: MIT
Platform: UNKNOWN
Classifier: Programming Language :: Python :: 3
Classifier: License :: OSI Approved :: MIT License
Classifier: Operating System :: OS Independent
Classifier: Development Status :: 3 - Alpha
Requires-Python: >=3.6.0
Requires-Dist: pandas (>=0.20.0)
Requires-Dist: openpyxl (>=2.5.0)
